CHANGELOG.md
LICENSE
MANIFEST.in
README.md
setup.cfg
setup.py
pip_services_commons/__init__.py
pip_services_commons.egg-info/PKG-INFO
pip_services_commons.egg-info/SOURCES.txt
pip_services_commons.egg-info/dependency_links.txt
pip_services_commons.egg-info/requires.txt
pip_services_commons.egg-info/top_level.txt
pip_services_commons.egg-info/zip-safe
pip_services_commons/auth/CredentialParams.py
pip_services_commons/auth/CredentialResolver.py
pip_services_commons/auth/DefaultCredentialStoreFactory.py
pip_services_commons/auth/ICredentialStore.py
pip_services_commons/auth/MemoryCredentialStore.py
pip_services_commons/auth/__init__.py
pip_services_commons/build/CompositeFactory.py
pip_services_commons/build/CreateException.py
pip_services_commons/build/Factory.py
pip_services_commons/build/IFactory.py
pip_services_commons/build/__init__.py
pip_services_commons/cache/CacheEntry.py
pip_services_commons/cache/DefaultCacheFactory.py
pip_services_commons/cache/ICache.py
pip_services_commons/cache/MemoryCache.py
pip_services_commons/cache/NullCache.py
pip_services_commons/cache/__init__.py
pip_services_commons/commands/Command.py
pip_services_commons/commands/CommandSet.py
pip_services_commons/commands/Event.py
pip_services_commons/commands/ICommand.py
pip_services_commons/commands/ICommandIntercepter.py
pip_services_commons/commands/ICommandable.py
pip_services_commons/commands/IEvent.py
pip_services_commons/commands/IEventListener.py
pip_services_commons/commands/InterceptedCommand.py
pip_services_commons/commands/__init__.py
pip_services_commons/config/ConfigParams.py
pip_services_commons/config/ConfigReader.py
pip_services_commons/config/DefaultConfigReaderFactory.py
pip_services_commons/config/FileConfigReader.py
pip_services_commons/config/IConfigReader.py
pip_services_commons/config/IConfigurable.py
pip_services_commons/config/IReconfigurable.py
pip_services_commons/config/JsonConfigReader.py
pip_services_commons/config/MemoryConfigReader.py
pip_services_commons/config/NameResolver.py
pip_services_commons/config/OptionsResolver.py
pip_services_commons/config/YamlConfigReader.py
pip_services_commons/config/__init__.py
pip_services_commons/connect/ConnectionParams.py
pip_services_commons/connect/ConnectionResolver.py
